{

    "tfUserMessage": {
        "font": "24px Arial",
        "color": "#000",
        "x": 1260,
        "y": 552,
        "lineWidth": 1020,
        "lineHeight": 28,
        "textAlign": "center"
    },

    "tfErrorCode": {
        "font": "20px Arial",
        "color": "#000",
        "x": 1720,
        "y": 782
    },

    "tfDebugMessage": {
        "font": "20px Arial",
        "color": "#000",
        "x": 742,
        "y": 1008,
        "lineWidth": 950,
        "lineHeight": 24
    },

    "tfSessionId": {
        "font": "20px Arial",
        "color": "#000",
        "x": 876,
        "y": 850
    },

    "tfTime": {
        "font": "20px Arial",
        "color": "#000",
        "x": 876,
        "y": 876
    },

    "tfGamePlayId": {
        "font": "20px Arial",
        "color": "#000",
        "x": 876,
        "y": 900
    },

    "tfGameName": {
        "font": "20px Arial",
        "color": "#000",
        "x": 876,
        "y": 926
    },

    "tfAccount": {
        "font": "20px Arial",
        "color": "#000",
        "x": 1456,
        "y": 876
    },

    "tfLanguage": {
        "font": "20px Arial",
        "color": "#000",
        "x": 1456,
        "y": 898
    },

    "tfPlayerName": {
        "font": "20px Arial",
        "color": "#000",
        "x": 1456,
        "y": 926
    },

    "tfSite": {
        "font": "20px Arial",
        "color": "#000",
        "x": 1456,
        "y": 948
    },

    "btnContactSupportData": {
        "width": 156,
        "height": 42
    },

    "btnContactSupport": {
        "x": 1202,
        "y": 760
    }

}

